README.md
setup.py
aggregator/example.py
aggregator/utils/Aggregator.py
aggregator/utils/__init__.py
aggregator/utils/functions.py
aggregator/utils/graph_iterator.py
aggregator/utils/GCN/Aggregation_Module.py
aggregator/utils/GCN/GCN.py
aggregator/utils/GCN/Message_Module.py
aggregator/utils/GCN/Prediction_Module.py
feature_aggregator.egg-info/PKG-INFO
feature_aggregator.egg-info/SOURCES.txt
feature_aggregator.egg-info/dependency_links.txt
feature_aggregator.egg-info/top_level.txt