Metadata-Version: 2.1
Name: feature-aggregator
Version: 0.1.0
Summary: Automate feature aggregation
Home-page: https://github.com/Daahorst/Aggregator
Author: François-Xavier Devailly, Xinyue Tan
Author-email: francois-xavier.devailly@hec.ca, xinyue.tan@hec.ca
License: Apache-2.0
Platform: UNKNOWN
